konnyaku_gpt/__init__.py
konnyaku_gpt/data_models.py
konnyaku_gpt/srt_export.py
konnyaku_gpt/transcription_correction.py
konnyaku_gpt/tricks.py
konnyaku_gpt/utils.py
konnyaku_gpt/many_clips_transcription_correction/__init__.py
konnyaku_gpt/many_clips_transcription_correction/many_clips_batched_corrector.py
konnyaku_gpt/many_clips_transcription_correction/many_clips_transcription_corrector.py
konnyaku_gpt/models/__init__.py
konnyaku_gpt/models/base.py
konnyaku_gpt/models/blip2_opt.py
konnyaku_gpt/models/blip_large.py
konnyaku_gpt/models/chat_completion.py
konnyaku_gpt/models/dummy_chat_completion_service.py
konnyaku_gpt/models/image_to_text.py
konnyaku_gpt/models/transcriber.py
konnyaku_gpt/models/whisper.py
konnyaku_gpt/models/whisper_cloud.py
konnyaku_gpt/models/gpt/__init__.py
konnyaku_gpt/models/gpt/gpt4.py
konnyaku_gpt/models/gpt/gpt_35_turbo.py
konnyaku_gpt/models/gpt/openai_gpt_server.py
konnyaku_gpt/subtitle_generation/__init__.py
konnyaku_gpt/subtitle_generation/default_generator.py
konnyaku_gpt/subtitle_generation/multimedia_llm_subtitle_generator.py
konnyaku_gpt/subtitle_generation/subtitle_generator.py
konnyaku_gpt/transcription_correction/__init__.py
konnyaku_gpt/transcription_correction/dummy_corrector.py
konnyaku_gpt/transcription_correction/multi_round_corrector.py
konnyaku_gpt/transcription_correction/simple_corrector.py
konnyaku_gpt/transcription_correction/transcription_corrector.py
konnyaku_gpt-0.0.1.dist-info/METADATA
konnyaku_gpt-0.0.1.dist-info/WHEEL
konnyaku_gpt-0.0.1.dist-info/licenses/LICENSE
konnyaku_gpt-0.0.1.dist-info/RECORD
